skctr/__init__.py
skctr/cli.py
skctr/skctr.py
scikit_ctr-0.1.0.dist-info/AUTHORS.rst
scikit_ctr-0.1.0.dist-info/LICENSE
scikit_ctr-0.1.0.dist-info/METADATA
scikit_ctr-0.1.0.dist-info/WHEEL
scikit_ctr-0.1.0.dist-info/entry_points.txt
scikit_ctr-0.1.0.dist-info/top_level.txt
scikit_ctr-0.1.0.dist-info/RECORD
