Metadata-Version: 2.1
Name: scikit-ctr
Version: 0.1.0
Summary: A scikit extends for Click-Through-Rate prediction.
Home-page: https://github.com/classtag/scikit-ctr
Author: Duo An
Author-email: anduo@qq.com
License: MIT license
Keywords: scikit,ctr
Platform: UNKNOWN
Classifier: Development Status :: 2 - Pre-Alpha
Classifier: Intended Audience :: Developers
Classifier: License :: OSI Approved :: MIT License
Classifier: Natural Language :: English
Classifier: Programming Language :: Python :: 3
Classifier: Programming Language :: Python :: 3.6
Requires-Python: >3.6
Requires-Dist: scikit-learn (>=20.0)
Requires-Dist: Click (>=6.0)
